_error_handler_version.py
error_handler/__init__.py
error_handler/_extra.py
error_handler/callback.py
error_handler/context_manager.py
error_handler/core.py
error_handler/decorator.py
error_handler/pipe.py
error_handler/py.typed
error_handler/result.py
error_handler/stream.py
error_handler/types.py
seviper-0.1.1.dist-info/METADATA
seviper-0.1.1.dist-info/WHEEL
seviper-0.1.1.dist-info/RECORD
